bromium-0.6.2.dist-info/METADATA
bromium-0.6.2.dist-info/WHEEL
bromium-0.6.2.dist-info/licenses/LICENSE
bromium/__init__.py
bromium/__init__.pyi
bromium/bromium.cp312-win_amd64.pyd
bromium/py.typed
bromium-0.6.2.dist-info/RECORD
