Metadata-Version: 2.4
Name: bromium
Version: 0.6.2
Classifier: Programming Language :: Rust
Classifier: Programming Language :: Python :: Implementation :: CPython
Classifier: Programming Language :: Python :: Implementation :: PyPy
License-File: LICENSE
Summary: A Python extension for UI Automation on Windows.
Keywords: windows,automation,testing,ui,scripting
Author-email: Daniel Grass <dani.grass@bluewin.ch>
Requires-Python: >=3.12
